async_ip_rotator/ClientSession.py
async_ip_rotator/IpRotator.py
async_ip_rotator/__init__.py
async_ip_rotator-0.1.0.dist-info/LICENSE
async_ip_rotator-0.1.0.dist-info/METADATA
async_ip_rotator-0.1.0.dist-info/WHEEL
async_ip_rotator-0.1.0.dist-info/top_level.txt
async_ip_rotator-0.1.0.dist-info/RECORD
