Metadata-Version: 2.1
Name: async-ip-rotator
Version: 0.1.0
Summary: Async IP Rotator ofuscates your requests' IP via AWS gateways.
Author-email: Jakub Pruzinec <j.pruzinec@gmail.com>
Requires-Python: >=3
License-File: LICENSE
Requires-Dist: aiohttp
Requires-Dist: aioboto3
